mcp_yahoo_finance/__init__.py
mcp_yahoo_finance/__main__.py
mcp_yahoo_finance/py.typed
mcp_yahoo_finance/server.py
mcp_yahoo_finance/utils.py
no_use_tools-0.0.6.dist-info/METADATA
no_use_tools-0.0.6.dist-info/WHEEL
no_use_tools-0.0.6.dist-info/entry_points.txt
no_use_tools-0.0.6.dist-info/licenses/LICENSE
no_use_tools-0.0.6.dist-info/RECORD
