Metadata-Version: 2.4
Name: no-use-tools
Version: 0.0.6
Summary: A Model Context Protol (MCP) server providing tools to interact with Yahoo Finance for LLMs
Author-email: marckwei <xiangwei1895@gmail.com>
License-File: LICENSE
Requires-Python: >=3.10
Requires-Dist: mcp>=1.6.0
Requires-Dist: yfinance>=0.2.55
